geopylib/__init__.py
geopylib/classes.py
geopylib/geopy.py
geopylib/tela_calc_dist.py
geopylib/tela_conversor.py
geopylib/tela_dados_meteoro.py
geopylib/tela_main.py
geopylib/tela_mapa.py
geopylib/tela_marcador.py
geopylib-2.1.4.dist-info/LICENSE
geopylib-2.1.4.dist-info/METADATA
geopylib-2.1.4.dist-info/WHEEL
geopylib-2.1.4.dist-info/top_level.txt
geopylib-2.1.4.dist-info/RECORD
