Metadata-Version: 2.1
Name: geopylib
Version: 2.1.4
Summary: Pacote para visualizar mapa
Home-page: https://github.com/RuanC4rlos/GeoPyLib
Author: Ruan e Natan
Author-email: crrc1920@gmail.com
Project-URL: Bug Tracker, https://github.com/RuanC4rlos/GeoPyLib/ProjMapa
Classifier: Programming Language :: Python :: 3
Classifier: License :: OSI Approved :: MIT License
Classifier: Operating System :: OS Independent
Requires-Python: >=3.8
License-File: LICENSE
